{
  "dataset": "/content/data/ASL_Alphabet_Dataset/asl_alphabet_train",
  "output": "/content/asl-translator/models/mobilenet_v3_small.pt",
  "classes": [
    "A",
    "B",
    "C",
    "D",
    "E",
    "F",
    "G",
    "H",
    "I",
    "J",
    "K",
    "L",
    "M",
    "N",
    "O",
    "P",
    "Q",
    "R",
    "S",
    "T",
    "U",
    "V",
    "W",
    "X",
    "Y",
    "Z",
    "del",
    "nothing",
    "space"
  ],
  "architecture": "mobilenet_v3_small",
  "pretrained": false,
  "trainable_parameters": 1547581,
  "best_val_accuracy": 0.965,
  "test": {
    "accuracy": 0.9635,
    "total": 33462,
    "per_class": [
      {
        "class": "A",
        "accuracy": 0.9758,
        "count": 1240
      },
      {
        "class": "B",
        "accuracy": 0.9734,
        "count": 1241
      },
      {
        "class": "C",
        "accuracy": 0.9871,
        "count": 1159
      },
      {
        "class": "D",
        "accuracy": 0.9516,
        "count": 1158
      },
      {
        "class": "E",
        "accuracy": 0.9504,
        "count": 1109
      },
      {
        "class": "F",
        "accuracy": 0.9807,
        "count": 1192
      },
      {
        "class": "G",
        "accuracy": 0.9585,
        "count": 1180
      },
      {
        "class": "H",
        "accuracy": 0.9831,
        "count": 1241
      },
      {
        "class": "I",
        "accuracy": 0.9569,
        "count": 1183
      },
      {
        "class": "J",
        "accuracy": 0.9891,
        "count": 1096
      },
      {
        "class": "K",
        "accuracy": 0.9688,
        "count": 1153
      },
      {
        "class": "L",
        "accuracy": 0.9792,
        "count": 1155
      },
      {
        "class": "M",
        "accuracy": 0.9046,
        "count": 1237
      },
      {
        "class": "N",
        "accuracy": 0.8779,
        "count": 1228
      },
      {
        "class": "O",
        "accuracy": 0.9791,
        "count": 1198
      },
      {
        "class": "P",
        "accuracy": 0.9483,
        "count": 1142
      },
      {
        "class": "Q",
        "accuracy": 0.9959,
        "count": 1224
      },
      {
        "class": "R",
        "accuracy": 0.9892,
        "count": 1207
      },
      {
        "class": "S",
        "accuracy": 0.9812,
        "count": 1226
      },
      {
        "class": "T",
        "accuracy": 0.9017,
        "count": 1231
      },
      {
        "class": "U",
        "accuracy": 0.9542,
        "count": 1222
      },
      {
        "class": "V",
        "accuracy": 0.9074,
        "count": 1156
      },
      {
        "class": "W",
        "accuracy": 0.9686,
        "count": 1177
      },
      {
        "class": "X",
        "accuracy": 0.9633,
        "count": 1254
      },
      {
        "class": "Y",
        "accuracy": 0.9799,
        "count": 1244
      },
      {
        "class": "Z",
        "accuracy": 0.9848,
        "count": 1052
      },
      {
        "class": "del",
        "accuracy": 0.9914,
        "count": 1051
      },
      {
        "class": "nothing",
        "accuracy": 0.9827,
        "count": 462
      },
      {
        "class": "space",
        "accuracy": 1.0,
        "count": 1044
      }
    ],
    "top_mistakes": [
      {
        "true": "N",
        "predicted": "M",
        "count": 77
      },
      {
        "true": "V",
        "predicted": "K",
        "count": 72
      },
      {
        "true": "T",
        "predicted": "S",
        "count": 63
      },
      {
        "true": "M",
        "predicted": "N",
        "count": 43
      },
      {
        "true": "E",
        "predicted": "S",
        "count": 39
      },
      {
        "true": "U",
        "predicted": "R",
        "count": 36
      },
      {
        "true": "N",
        "predicted": "S",
        "count": 33
      },
      {
        "true": "T",
        "predicted": "A",
        "count": 32
      },
      {
        "true": "M",
        "predicted": "A",
        "count": 31
      },
      {
        "true": "P",
        "predicted": "G",
        "count": 30
      },
      {
        "true": "N",
        "predicted": "A",
        "count": 30
      },
      {
        "true": "M",
        "predicted": "S",
        "count": 25
      },
      {
        "true": "I",
        "predicted": "E",
        "count": 23
      },
      {
        "true": "P",
        "predicted": "H",
        "count": 20
      },
      {
        "true": "B",
        "predicted": "A",
        "count": 17
      }
    ]
  },
  "history": [
    {
      "epoch": 1,
      "train_loss": 0.8381,
      "train_accuracy": 0.7347,
      "val_loss": 0.2589,
      "val_accuracy": 0.9147
    },
    {
      "epoch": 2,
      "train_loss": 0.2147,
      "train_accuracy": 0.9304,
      "val_loss": 0.1344,
      "val_accuracy": 0.957
    },
    {
      "epoch": 3,
      "train_loss": 0.1452,
      "train_accuracy": 0.9534,
      "val_loss": 0.1131,
      "val_accuracy": 0.965
    }
  ]
}